photon/__init__.py
photon/gamma.py
photon/layers.py
photon/losses.py
photon/metrics.py
photon/models.py
photon/optimizers.py
photon/options.py
photon/runs.py
photon/utils.py
photon_ml-0.1.2.dist-info/LICENSE
photon_ml-0.1.2.dist-info/METADATA
photon_ml-0.1.2.dist-info/WHEEL
photon_ml-0.1.2.dist-info/top_level.txt
photon_ml-0.1.2.dist-info/RECORD
