Metadata-Version: 2.1
Name: photon-ml
Version: 0.1.2
Summary: ML Framework
Home-page: https://github.com/sequenzia/photon
Author: Stephen Sequenzia
Author-email: sequenzia@gmail.com
Project-URL: Bug Tracker, https://github.com/sequenzia/photon/issues
Classifier: Programming Language :: Python :: 3
Classifier: License :: OSI Approved :: MIT License
Classifier: Operating System :: OS Independent
Requires-Python: >=3.7
License-File: LICENSE
Requires-Dist: tensorflow (>=2.7)
Requires-Dist: pandas (>=1.2)
Requires-Dist: numpy (>=1.2)
Requires-Dist: tables
Requires-Dist: pyarrow
Requires-Dist: sklearn
